oarepo_generated_ui/__init__.py
oarepo_generated_ui/config.py
oarepo_generated_ui/ext.py
oarepo_generated_ui/theme/__init__.py
oarepo_generated_ui/theme/webpack.py
oarepo_generated_ui/theme/assets/semantic-ui/js/oarepo_generated_ui/hooks.jsx
oarepo_generated_ui/theme/assets/semantic-ui/js/oarepo_generated_ui/index.js
oarepo_generated_ui/theme/assets/semantic-ui/js/oarepo_generated_ui/layout.js
oarepo_generated_ui/theme/assets/semantic-ui/js/oarepo_generated_ui/util.jsx
oarepo_generated_ui/theme/assets/semantic-ui/js/oarepo_generated_ui/context/data.jsx
oarepo_generated_ui/theme/assets/semantic-ui/js/oarepo_generated_ui/context/index.js
oarepo_generated_ui/theme/assets/semantic-ui/js/oarepo_generated_ui/ui_components/SeparatorComponent.jsx
oarepo_generated_ui/theme/assets/semantic-ui/js/oarepo_generated_ui/ui_components/index.js
oarepo_generated_ui/theme/assets/semantic-ui/js/oarepo_generated_ui/ui_components/withDataArray.jsx
oarepo_generated_ui-1.0.5.dist-info/AUTHORS. md
oarepo_generated_ui-1.0.5.dist-info/LICENSE
oarepo_generated_ui-1.0.5.dist-info/METADATA
oarepo_generated_ui-1.0.5.dist-info/WHEEL
oarepo_generated_ui-1.0.5.dist-info/entry_points.txt
oarepo_generated_ui-1.0.5.dist-info/top_level.txt
oarepo_generated_ui-1.0.5.dist-info/RECORD
