Metadata-Version: 2.1
Name: oarepo-generated-ui
Version: 1.0.5
Summary: Generation of UI parts from a layout configuration
Home-page: https://github.com/oarepo/oarepo-generated-ui
Author: CESNET
Author-email: bauer@cesnet.cz
License: MIT
Keywords: oarepo generated ui
Platform: any
Classifier: Development Status :: 5 - Production/Stable
Requires-Python: >=3.6
Requires-Dist: Babel (>=2.8)
Requires-Dist: invenio-assets (>=1.2.7)
Requires-Dist: invenio-base (>=1.2.11)
Requires-Dist: invenio-i18n (>=1.3.2)
Provides-Extra: tests
Requires-Dist: invenio-db (>=1.0.8) ; extra == 'tests'
Requires-Dist: pytest-invenio (>=1.4.2) ; extra == 'tests'
